README.md
setup.py
zenchi/__init__.py
zenchi/api.py
zenchi/cache.py
zenchi/codes.py
zenchi/crypto.py
zenchi/errors.py
zenchi/settings.py
zenchi.egg-info/PKG-INFO
zenchi.egg-info/SOURCES.txt
zenchi.egg-info/dependency_links.txt
zenchi.egg-info/requires.txt
zenchi.egg-info/top_level.txt
zenchi/mappings/__init__.py
zenchi/mappings/conversions.py
zenchi/mappings/episode.py
zenchi/mappings/group.py
zenchi/mappings/group_status.py